whikoperator/__init__.py
whikoperator/functions.py
whikoperator/main.py
whikoperator/settings.py
whikoperator/configs/__init__.py
whikoperator/configs/cam_count.py
whikoperator/photos/Tests.png
whikoperator/tests/__init__.py
whikoperator/tests/functions_test.py
whikoperator/tests/main_test.py
whikoperator/tests/settings_test.py
whikoperator/tests/shot_test.py
ghik_frame-0.0.1.dist-info/LICENSE
ghik_frame-0.0.1.dist-info/METADATA
ghik_frame-0.0.1.dist-info/WHEEL
ghik_frame-0.0.1.dist-info/top_level.txt
ghik_frame-0.0.1.dist-info/RECORD
